pysenseword/__init__.py
pysenseword/default_dict.py
pysenseword/detect.py
pysenseword/dict_deduplicate.py
pysenseword-1.0.0.dist-info/LICENSE
pysenseword-1.0.0.dist-info/METADATA
pysenseword-1.0.0.dist-info/WHEEL
pysenseword-1.0.0.dist-info/top_level.txt
pysenseword-1.0.0.dist-info/RECORD
