Metadata-Version: 2.1
Name: pysenseword
Version: 1.0.0
Summary: A module to detect sense words
Home-page: https://github.com/ILoveScratch2/PySenseWord
Author: ILoveScratch
Author-email: ilovescratch@ilovescratch.us.kg
License: MIT
Classifier: License :: OSI Approved :: MIT License
Classifier: Programming Language :: Python
Classifier: Programming Language :: Python :: 3
Classifier: Programming Language :: Python :: 3.6
Classifier: Programming Language :: Python :: Implementation :: CPython
Classifier: Programming Language :: Python :: Implementation :: PyPy
Requires-Python: >=3.6.0
License-File: LICENSE
